{
  "_class": "shapeGroup",
  "booleanOperation": -1,
  "clippingMaskMode": 0,
  "do_objectID": "08DA6FA8-F740-482D-A9A0-37FD662EE52F",
  "exportOptions": {
    "_class": "exportOptions",
    "exportFormats": [
    ],
    "includedLayerIds": [
    ],
    "layerOptions": 0,
    "shouldTrim": false
  },
  "frame": {
    "_class": "rect",
    "constrainProportions": false,
    "height": 13.68000000000006,
    "width": 40.64000000000033,
    "x": 688.4899999999998,
    "y": 168.5
  },
  "groupLayout": {
    "_class": "MSImmutableFreeformGroupLayout"
  },
  "hasClickThrough": false,
  "hasClippingMask": false,
  "isFixedToViewport": false,
  "isFlippedHorizontal": false,
  "isFlippedVertical": false,
  "isLocked": false,
  "isVisible": true,
  "layerListExpandedType": 1,
  "layers": [
    {
      "class": "shapePath",
      "id": "91F6D204-7B52-4CAC-82F3-AD4523E82F67"
    },
    {
      "class": "shapePath",
      "id": "8BA0F665-AD64-4A71-9703-D9F10DB48F9E"
    },
    {
      "class": "shapePath",
      "id": "BF9F1805-3481-4F19-9490-6AFF67DE0285"
    },
    {
      "class": "shapePath",
      "id": "5786752F-3E43-4C32-87E0-9325BA191141"
    },
    {
      "class": "shapePath",
      "id": "49D26BD5-8C45-4EDF-BC55-01E063338169"
    },
    {
      "class": "shapePath",
      "id": "6FFF131D-BC90-4462-BF74-78400B2E90D9"
    },
    {
      "class": "shapePath",
      "id": "0A03E597-CD27-43B8-A89C-99A5EEEE4C19"
    },
    {
      "class": "shapePath",
      "id": "E340CBD6-243E-4524-AA45-36990294C61B"
    }
  ],
  "maintainScrollPosition": false,
  "name": "Shape",
  "nameIsFixed": false,
  "resizingConstraint": 63,
  "resizingType": 0,
  "rotation": 0,
  "shouldBreakMaskChain": false,
  "style": {
    "_class": "style",
    "blur": {
      "_class": "blur",
      "center": "{0.5, 0.5}",
      "isEnabled": false,
      "motionAngle": 0,
      "radius": 10,
      "saturation": 1,
      "type": 0
    },
    "borderOptions": {
      "_class": "borderOptions",
      "dashPattern": [
      ],
      "isEnabled": true,
      "lineCapStyle": 0,
      "lineJoinStyle": 0
    },
    "borders": [
    ],
    "colorControls": {
      "_class": "colorControls",
      "brightness": 0,
      "contrast": 1,
      "hue": 0,
      "isEnabled": false,
      "saturation": 1
    },
    "contextSettings": {
      "_class": "graphicsContextSettings",
      "blendMode": 0,
      "opacity": 1
    },
    "do_objectID": "9C5D08E9-E8D0-4688-AECB-906C743C87DC",
    "endMarkerType": 0,
    "fills": [
      {
        "_class": "fill",
        "color": {
          "_class": "color",
          "alpha": 1,
          "blue": 0.5019607843137255,
          "green": 0.5019607843137255,
          "red": 0.5019607843137255
        },
        "contextSettings": {
          "_class": "graphicsContextSettings",
          "blendMode": 0,
          "opacity": 1
        },
        "fillType": 0,
        "gradient": {
          "_class": "gradient",
          "elipseLength": 0,
          "from": "{0.5, 0}",
          "gradientType": 0,
          "stops": [
            {
              "_class": "gradientStop",
              "color": {
                "_class": "color",
                "alpha": 1,
                "blue": 1,
                "green": 1,
                "red": 1
              },
              "position": 0
            },
            {
              "_class": "gradientStop",
              "color": {
                "_class": "color",
                "alpha": 1,
                "blue": 0,
                "green": 0,
                "red": 0
              },
              "position": 1
            }
          ],
          "to": "{0.5, 1}"
        },
        "isEnabled": true,
        "noiseIndex": 0,
        "noiseIntensity": 0,
        "patternFillType": 1,
        "patternTileScale": 1
      }
    ],
    "innerShadows": [
    ],
    "miterLimit": 10,
    "shadows": [
    ],
    "startMarkerType": 0,
    "windingRule": 0
  },
  "windingRule": 0
}